<paragraph xmlns:gate="http://www.gate.ac.uk" gate:gateId="0" gate:annotMaxId="358"><Location gate:gateId="288" locType="city" rule1="Location1" gate:matches="288;302" rule2="LocFinal">Adler</Location>, Larry (Lawrence), harmonica player; <Event_Birth gate:gateId="357" RE="Feb. 10, 1914" Pred="birth" Pred-tyoe="time"><Birth gate:gateId="355" predict="birth">b.</Birth> <Location gate:gateId="291" rule1="Location1" locType="city" rule2="LocFinal">Baltimore</Location>, <Date gate:gateId="292" rule1="DateNameRev" kind="date" rule2="DateOnlyFinal">Feb. 10, 1914</Date></Event_Birth>. He won a harmonica contest at 13 for the best rendition of Beethoven&apos;s Minuet in G. He has appeared in numerous revues; also gave concerts as soloist with piano and with orchestra, as well as command performances for King George VI, King Gustav of <Location gate:gateId="296" rule1="Location1" locType="country" rule2="LocFinal">Sweden</Location> and <Location gate:gateId="311" rule ="LocConjLoc2">Presidents</Location> Roosevelt and Truman. In <Date gate:gateId="299" rule1="TempYear3" kind="date" rule2="YearOnlyFinal">1940</Date>, determined to learn to read music, he took lessons with Ernst Toch. Darius Milhaud wrote a Suite for harmonica and orch. for <Location gate:gateId="302" locType="city" rule1="Location1" gate:matches="288;302" rule2="LocFinal">Adler</Location>, which he played on <Date gate:gateId="303" rule1="DateNameRev" kind="date" rule2="DateOnlyFinal">Nov. 16, 1945</Date> with the Philadelphia Orch. </paragraph>