<event><Object>Ferrara</Object><Verb>be born</Verb><Date>1743</Date></event><event><Object>Parma</Object></event><event><Verb>JobTitle</Verb><JobTitle>father</JobTitle><Object>Lambertini</Object></event><event><Location>triumphant debut at Florence</Location><Date>1764</Date><Verb>made</Verb></event><event><Object>Mozart</Object><Object>lovely voice</Object><Verb>wrote</Verb></event><event><Object>incredibly high range</Object></event><event><Verb>JobTitle</Verb><JobTitle>Italian composer</JobTitle><Date>1780</Date></event><event><Object>concerts</Object><Verb>performed</Verb></event><event><Object>compass</Object><Object>octaves</Object><Object>CMU</Object><Verb>was</Verb></event>